vhmap/__init__.py
vhmap/color.html
vhmap/config.py
vhmap/mcom.py
vhmap/mcom_def.py
vhmap/mcom_read.py
vhmap/mcom_rec.py
vhmap/mcom_replay.py
vhmap/mcom_rt.py
vhmap/mcom_test.py
vhmap/mcom_testing.py
vhmap/mcom_v2d.py
vhmap/read_batch_data.py
vhmap/read_group_replay.ipynb
vhmap/seaborn_defaults.py
vhmap/threejs_replay.py
vhmap/__pycache__/__init__.cpython-311.pyc
vhmap/__pycache__/mcom.cpython-311.pyc
vhmap/__pycache__/mcom_def.cpython-311.pyc
vhmap/__pycache__/mcom_rec.cpython-311.pyc
vhmap/__pycache__/read_batch_data.cpython-311.pyc
vhmap/__pycache__/seaborn_defaults.cpython-311.pyc
vhmap/examples/__init__.py
vhmap/examples/nb.py
vhmap/examples/nb_3body_specials.py
vhmap/examples/nb_nbody_chaos.py
vhmap/examples/nb_nbody_specials.py
vhmap/examples/nb_ode.py
vhmap/examples/robot.py
vhmap/examples/test_pitch_roll.py
vhmap/examples/初始条件
vhmap/md_imgs/HMP_CONF.svg
vhmap/md_imgs/hmp2g_timeline.svg
vhmap/md_imgs/multi_team.jpg
vhmap/md_imgs/simple_framework.jpg
vhmap/md_imgs/timeline.jpg
vhmap/md_imgs/动画11.gif
vhmap/md_imgs/动画12-1.gif
vhmap/md_imgs/动画13.gif
vhmap/md_imgs/动画9.gif
vhmap/md_imgs/动画x7.gif
vhmap/threejsmod/build/pako.min.js
vhmap/threejsmod/build/three.js
vhmap/threejsmod/build/three.min.js
vhmap/threejsmod/build/three.module.js
vhmap/threejsmod/examples/abc.html
vhmap/threejsmod/examples/abc.js
vhmap/threejsmod/examples/abc_init.js
vhmap/threejsmod/examples/abc_io.js
vhmap/threejsmod/examples/abc_obj.js
vhmap/threejsmod/examples/abc_parse.js
vhmap/threejsmod/examples/abc_rt.html
vhmap/threejsmod/examples/abc_rt.js
vhmap/threejsmod/examples/files/missile.fbx
vhmap/threejsmod/examples/files/plane.fbx
vhmap/threejsmod/examples/files/thumbnails.svg
vhmap/threejsmod/examples/fonts/LICENSE
vhmap/threejsmod/examples/fonts/README.md
vhmap/threejsmod/examples/fonts/gentilis_bold.typeface.json
vhmap/threejsmod/examples/fonts/gentilis_regular.typeface.json
vhmap/threejsmod/examples/fonts/helvetiker_bold.typeface.json
vhmap-4.2.0.dist-info/LICENSE
vhmap-4.2.0.dist-info/METADATA
vhmap-4.2.0.dist-info/WHEEL
vhmap-4.2.0.dist-info/top_level.txt
vhmap-4.2.0.dist-info/RECORD
