Metadata-Version: 2.1
Name: vhmap
Version: 4.2.0
Summary: Advanced 3D visualizer for researchers
Home-page: https://github.com/binary-husky/vhmap
Author: Qingxu
Author-email: 505030475@qq.com
Project-URL: Bug Tracker, https://github.com/binary-husky/vhmap/issues
Classifier: Programming Language :: Python :: 3
Classifier: License :: OSI Approved :: MIT License
Classifier: Operating System :: OS Independent
Requires-Python: >=3.6
License-File: LICENSE
Requires-Dist: flask
Requires-Dist: waitress
Requires-Dist: numpy
Requires-Dist: scipy
Requires-Dist: colorama
Requires-Dist: setproctitle
